maestro/__init__.py
maestro/__main__.py
maestro/__version__.py
maestro/config.py
maestro/helpers.py
maestro/icon.py
maestro/jit_funcs.py
maestro/mac_presence.py
maestro/main.py
maestro_music-2.0.5.dist-info/LICENSE
maestro_music-2.0.5.dist-info/METADATA
maestro_music-2.0.5.dist-info/WHEEL
maestro_music-2.0.5.dist-info/entry_points.txt
maestro_music-2.0.5.dist-info/top_level.txt
maestro_music-2.0.5.dist-info/RECORD
