Metadata-Version: 2.1
Name: maestro-music
Version: 2.0.5
Summary: A simple command line tool to play songs (or any audio files, really).
Home-page: https://github.com/PrajwalVandana/maestro-cli
Author: Prajwal Vandana
License: MIT
Keywords: music,sound,audio,music-player,cli,ogg,vorbis,ogg vorbis,flac,mp3,wav,spotify,youtube,audio-visualization,audio-visualizer
License-File: LICENSE
Requires-Dist: click
Requires-Dist: just-playback
Requires-Dist: music-tag
Requires-Dist: pillow
Requires-Dist: pypresence >=4.3.0
Requires-Dist: yt-dlp
Requires-Dist: spotdl
Requires-Dist: ytmusicapi
Requires-Dist: librosa
Requires-Dist: numba
Requires-Dist: numpy ~=1.26
Requires-Dist: keyring
Requires-Dist: requests
Requires-Dist: msgspec
Requires-Dist: syncedlyrics
Requires-Dist: pylrc
Requires-Dist: safer
Requires-Dist: grapheme
Requires-Dist: unidecode
Requires-Dist: pykakasi
Requires-Dist: translatepy
Requires-Dist: indic-transliteration
Requires-Dist: pyobjc-core ; sys_platform == "darwin"
Requires-Dist: pyobjc-framework-ApplicationServices ; sys_platform == "darwin"
Requires-Dist: pyobjc-framework-AVFoundation ; sys_platform == "darwin"
Requires-Dist: pyobjc-framework-Cocoa ; sys_platform == "darwin"
Requires-Dist: pyobjc-framework-CoreAudio ; sys_platform == "darwin"
Requires-Dist: pyobjc-framework-CoreMedia ; sys_platform == "darwin"
Requires-Dist: pyobjc-framework-MediaPlayer ; sys_platform == "darwin"
Requires-Dist: pyobjc-framework-Quartz ; sys_platform == "darwin"
Requires-Dist: windows-curses ; sys_platform == "win32"
